async_gfycat/__init__.py
async_gfycat/client.py
async_gfycat/errors.py
async_gfycat-1.0.2.dist-info/LICENSE
async_gfycat-1.0.2.dist-info/METADATA
async_gfycat-1.0.2.dist-info/WHEEL
async_gfycat-1.0.2.dist-info/top_level.txt
async_gfycat-1.0.2.dist-info/RECORD
