Metadata-Version: 2.1
Name: async-gfycat
Version: 1.0.2
Summary: An async wrapper for Gfycat API
Home-page: https://github.com/GreenArron/async-gfycat
Author: GreenArron
License: UNKNOWN
Project-URL: Bug Tracker, https://github.com/GreenArron/async-gfycat/issues
Keywords: gfycat,api,async
Platform: UNKNOWN
Classifier: Intended Audience :: Developers
Classifier: Natural Language :: English
Classifier: Programming Language :: Python :: 3.8
Classifier: Programming Language :: Python :: 3.9
Classifier: Programming Language :: Python :: 3.10
Classifier: License :: OSI Approved :: MIT License
Classifier: Operating System :: OS Independent
Classifier: Typing :: Typed
Requires-Python: >=3.8.0
License-File: LICENSE
Requires-Dist: aiohttp (<3.9.0,>=3.6.0)
